README.rst
setup.py
pymol_sketch/__init__.py
pymol_sketch/commands.py
pymol_sketch/geometry.py
pymol_sketch/shape.py
pymol_sketch/utils.py
pymol_sketch.egg-info/PKG-INFO
pymol_sketch.egg-info/SOURCES.txt
pymol_sketch.egg-info/dependency_links.txt
pymol_sketch.egg-info/top_level.txt
pymol_sketch.egg-info/zip-safe