Metadata-Version: 1.1
Name: pymol-sketch
Version: 0.1.0
Summary: A pymol command collection to sketch CGO
Home-page: https://github.com/lambdalisue/pymol-sketch
Author: Alisue
Author-email: lambdalisue@hashnote.net
License: MIT
Download-URL: https://github.com/lambdalisue/pymol-sketch/tarball/master
Keywords: pymol cgo
Platform: UNKNOWN
Classifier: Development Status :: 3 - Alpha
Classifier: Environment :: Plugins
Classifier: Intended Audience :: Science/Research
Classifier: License :: OSI Approved :: MIT License
Classifier: Programming Language :: Python
Classifier: Programming Language :: Python :: 2
Classifier: Programming Language :: Python :: 2.6
Classifier: Programming Language :: Python :: 2.7
